{"name": "Python Mk II", "overview_text": "There are 2 variants: Standard and Stellar. The Stellar version is listed in the Pre-Built Ships section via the main menu. The Standard variant has nearly identical Outfitting as normal ships. The Stellar variant is equipped by default with four Multi-Cannons and two Pulse Lasers.\nThe Mk II is highly lethal in combat. It comes with six hardpoint slots, four of which are Class 3 and the remainder Class 2s, making its potential damage output more akin to a large ship. This combined with its maneuverability makes the Python Mk II exceptionally well suited for combat activities such as Piracy, Bounty Hunting, Assassination, and Xeno Hunting.\nThe Mk II can carry a maximum of 96 t of cargo, which is dwarfed by the 294 t cargo capacity of the Mk I, making the Mk II much less effective for activities such as trading or mining compared to its predecessor. \nThe Mk II has a higher default unladen jump range of 18.11 ly versus the Mk I's 8.25 ly due to the 5C SCO-capable Frame Shift Drive coming preinstalled. When equipped with identical FSDs, the Mk II and Mk I have very similar jump ranges\u201419.93 ly and 19.48 ly, respectively. However, when outfitted for jump range, the difference is much larger\u201426.71 ly and 31.63 ly. The gap widens even more dramatically when engineering is added to the equation.\nThe Mk II was designed from the ground up for supercruise overcharge, giving it much better handling, less thermal load, less fuel consumption, and better acceleration and deceleration while using SCO compared to all previous ships.\n\nThe Python Mk II was the first new ship added to Elite Dangerous since the addition of the Mamba in 2018. Frontier announced in a Frontier Unlocked livestream that the Mk II will be added with a free update in 2024.  Elite partners got early access on a test server on 1 May 2024.[1] This ship became available for early access for 16,250 ARX on 7 May 2024. It became available for purchase using in-game credits on 7 Aug 2024. More purchase locations can be found on Inara.cz\nAll ships are highly customisable through the Outfitting menu of Station Services. Listed below is the default loadout for the Python Mk II.\n* (L) = Loaned Module\n\n", "infobox": {"overview": {"manufacturer": "Faulcon DeLacy", "years_produced": "3310-Present", "ship_type": "Combat", "cost": "67,527,361 CR", "insurance": "3,376,368 CR", "expansion": "N/A"}, "specifications": {"hangar_type": "N/A", "landing_pad_size": "Medium", "dimensions": "88.4m x 67.5m x 17.3m", "pilot_seats": "2", "multicrew": "Yes", "fighter_hangar": "No", "hull_mass": "450 t", "mass_lock_factor": "17", "armour": "504", "armour_hardness": "70", "shields": "316 MJ", "heat_capacity": "260", "fuel_capacity": "16 t", "manoeuvrability": "4", "top_speed": "261 m/s (default) 297 m/s (upgraded) ", "boost_speed": "352 m/s (default) 400 m/s (upgraded) ", "unladen_jump_range": "18.11 ly (default) 26.71 ly (upgraded) ", "cargo_capacity": "10 t (default) 96 t (max) "}, "outfitting": {"hardpoints": "6x Utility Mounts 2x Medium Hardpoints 4x Large Hardpoints ", "internal_compartments": "2x Class 1 Compartments 1x Class 2 Compartment 1x Class 3 Compartment 1x Class 4 Compartment 1x Class 6 Compartment ", "reserved_compartments": "N/A"}, "hardpoints": null}, "outfitting": {"small_hardpoint": [], "medium_hardpoint": [{"default_system": "Pulse Laser (L)", "default_rating": "F", "default_class": "1", "max_class": "2\n"}, {"default_system": "Pulse Laser (L)", "default_rating": "F", "default_class": "1", "max_class": "2\n"}], "large_hardpoint": [{"default_system": "Empty", "default_rating": "--", "default_class": "--", "max_class": "3\n"}, {"default_system": "Empty", "default_rating": "--", "default_class": "--", "max_class": "3\n"}, {"default_system": "Empty", "default_rating": "--", "default_class": "--", "max_class": "3\n"}, {"default_system": "Empty\n", "default_rating": "--\n", "default_class": "--\n", "max_class": "3\n"}], "utility_mount": [{"default_system": "Empty", "default_rating": "--", "default_class": "--", "max_class": "0\n"}, {"default_system": "Empty", "default_rating": "--", "default_class": "--", "max_class": "0\n"}, {"default_system": "Empty", "default_rating": "--", "default_class": "--", "max_class": "0\n"}, {"default_system": "Empty", "default_rating": "--", "default_class": "--", "max_class": "0\n"}, {"default_system": "Empty", "default_rating": "--", "default_class": "--", "max_class": "0\n"}, {"default_system": "Empty", "default_rating": "--", "default_class": "--", "max_class": "0\n"}], "bulkhead": {"default_system": "Lightweight Alloys", "default_rating": "C", "default_class": "1", "max_class": "1"}, "reactor_bay": {"default_system": "Power Plant", "default_rating": "E", "default_class": "6", "max_class": "6"}, "thrusters_mounting": {"default_system": "Thrusters", "default_rating": "E", "default_class": "6", "max_class": "6"}, "frame_shift_drive_housing": {"default_system": "Frame Shift Drive (SCO)", "default_rating": "C", "default_class": "5", "max_class": "5"}, "environment_control": {"default_system": "Life Support", "default_rating": "E", "default_class": "4", "max_class": "4"}, "power_coupling": {"default_system": "Power Distributor", "default_rating": "E", "default_class": "6", "max_class": "6"}, "sensor_suite": {"default_system": "Sensors", "default_rating": "E", "default_class": "5", "max_class": "5"}, "fuel_store": {"default_system": "Fuel Tank", "default_rating": "C", "default_class": "4", "max_class": "4"}, "internal_compartments": [{"default_system": "Shield Generator", "default_rating": "E", "default_class": "6", "max_class": "6\n"}, {"default_system": "Empty", "default_rating": "--", "default_class": "--", "max_class": "4\n"}, {"default_system": "Empty", "default_rating": "--", "default_class": "--", "max_class": "3\n"}, {"default_system": "Empty", "default_rating": "--", "default_class": "--", "max_class": "2\n"}, {"default_system": "Cargo Rack [x2]\n", "default_rating": "E", "default_class": "1", "max_class": "1\n"}, {"default_system": "Supercruise Assist", "default_rating": "E", "default_class": "1", "max_class": "1\n"}, {"default_system": "(PAS)", "default_rating": "I", "default_class": "1", "max_class": "1\n"}]}}